nontree/BiTree.py
nontree/NonTree.py
nontree/QuadTree.py
nontree/TreeMap.py
nontree/__init__.py
nontree/visualize.py
nontree-1.0.5.dist-info/METADATA
nontree-1.0.5.dist-info/WHEEL
nontree-1.0.5.dist-info/licenses/LICENSE
nontree-1.0.5.dist-info/RECORD
