Metadata-Version: 2.1
Name: nontree
Version: 1.0.5
Summary: A package for n-tree 2D data structures similar to and including quadtree, with mapping to payload data.
Project-URL: homepage, https://github.com/iehgit/nontree
Project-URL: repository, https://github.com/iehgit/nontree
Project-URL: documentation, https://pydocs.sedf.de/nontree
Project-URL: Bug Tracker, https://github.com/iehgit/nontree/issues
Author-email: Sebastian Dalfuß <py@sedf.de>
License-File: LICENSE
Classifier: License :: OSI Approved :: MIT License
Classifier: Operating System :: OS Independent
Classifier: Programming Language :: Python :: 3
Classifier: Topic :: Software Development :: Libraries :: Python Modules
Requires-Python: >=3.10
Provides-Extra: jit
Requires-Dist: numba; extra == 'jit'
Provides-Extra: visualization
Requires-Dist: matplotlib; extra == 'visualization'
